Metadata-Version: 1.1
Name: lfdeploy
Version: 1.2.5
Summary: Improved tfdeploy module
Home-page: https://github.com/LendFlo/Lendflo-tfdeploy
Author: Przemyslaw Winszczyk
Author-email: n3onix@gmail.com
License: UNKNOWN
Platform: UNKNOWN
Classifier: Programming Language :: Python :: 3
Classifier: License :: OSI Approved :: MIT License
Classifier: Operating System :: OS Independent
